gromologist/Crooks.py
gromologist/DihOpt.py
gromologist/Entries.py
gromologist/Gmx.py
gromologist/Mutant.py
gromologist/Parser.py
gromologist/Pdb.py
gromologist/Section.py
gromologist/Subsection.py
gromologist/ThDiff.py
gromologist/Topology.py
gromologist/Utils.py
gromologist/__init__.py
gromologist-0.330.dist-info/LICENSE
gromologist-0.330.dist-info/METADATA
gromologist-0.330.dist-info/WHEEL
gromologist-0.330.dist-info/entry_points.txt
gromologist-0.330.dist-info/top_level.txt
gromologist-0.330.dist-info/RECORD
