Metadata-Version: 2.1
Name: gromologist
Version: 0.330
Summary: Library to handle various GROMACS-related stuff
Author: Milosz Wieczor
Author-email: milafternoon@gmail.com
License: GNU GPLv3
License-File: LICENSE
Requires-Dist: numpy>=1.10.0
